happier/__init__.py
happier/__main__.py
happier/black_fmt.py
happier/main.py
happier/perform_autoflake.py
happier/sort_imports.py
happier/sources.py
happier/util.py
happier-0.1.0.dist-info/entry_points.txt
happier-0.1.0.dist-info/WHEEL
happier-0.1.0.dist-info/METADATA
happier-0.1.0.dist-info/RECORD
